pymodorogui/__init__.py
pymodorogui/__main__.py
pymodorogui/pymodoro.py
pymodorogui/resources/__init__.py
pymodorogui/resources/beep.wav
pymodorogui/resources/icon.png
pymodoro_gui-1.4.1.dist-info/LICENSE.txt
pymodoro_gui-1.4.1.dist-info/METADATA
pymodoro_gui-1.4.1.dist-info/WHEEL
pymodoro_gui-1.4.1.dist-info/top_level.txt
pymodoro_gui-1.4.1.dist-info/RECORD
