Metadata-Version: 2.1
Name: pymodoro-gui
Version: 1.4.1
Summary: A pomodoro app with a GUI for Windows
Home-page: https://github.com/Lcrs123/pymodoro-gui.git
Author: Lucas Camillo
Author-email: lucascamillo333@hotmail.com
License: GPL 3.0
Keywords: pomodoro,gui,windows,tkinter
Platform: UNKNOWN
Classifier: Development Status :: 5 - Production/Stable
Classifier: Intended Audience :: End Users/Desktop
Classifier: License :: OSI Approved :: GNU General Public License v3 (GPLv3)
Classifier: Programming Language :: Python :: 3.7
Classifier: Operating System :: Microsoft :: Windows
License-File: LICENSE.txt
